[{"bounds": {"northeast": {"lat": 54.0510099, "lng": -2.7998948}, "southwest": {"lat": 54.0467801, "lng": -2.8100467}}, "copyrights": "Map data \u00a92022", "legs": [{"distance": {"text": "1.0 km", "value": 999}, "duration": {"text": "4 mins", "value": 224}, "end_address": "12 Water St, Lancaster LA1 1HF, UK", "end_location": {"lat": 54.0510099, "lng": -2.7998948}, "start_address": "35 Wingate-Saul Rd, Lancaster LA1 5DW, UK", "start_location": {"lat": 54.0467801, "lng": -2.8094482}, "steps": [{"distance": {"text": "0.1 km", "value": 124}, "duration": {"text": "1 min", "value": 45}, "end_location": {"lat": 54.04783159999999, "lng": -2.8100467}, "html_instructions": "Head <b>north</b> on <b>Wingate-Saul Rd</b> toward <b>Anthony Rd</b>", "polyline": {"points": "k_{hI`vcPC?C@G@IDQJkAp@UJUJm@V"}, "start_location": {"lat": 54.0467801, "lng": -2.8094482}, "travel_mode": "DRIVING"}, {"distance": {"text": "0.2 km", "value": 218}, "duration": {"text": "1 min", "value": 36}, "end_location": {"lat": 54.0480988, "lng": -2.8067478}, "html_instructions": "Turn <b>right</b> onto <b>Westbourne Rd</b>", "maneuver": "turn-right", "polyline": {"points": "}e{hIxycPGoAE{@Ey@EuACs@Ey@EmACkAEkAAc@"}, "start_location": {"lat": 54.04783159999999, "lng": -2.8100467}, "travel_mode": "DRIVING"}, {"distance": {"text": "0.2 km", "value": 185}, "duration": {"text": "1 min", "value": 38}, "end_location": {"lat": 54.0485994, "lng": -2.8040831}, "html_instructions": "Continue onto <b>Meeting House Ln</b>", "polyline": {"points": "sg{hIdecPA{@EmAAQASCWAOCSGc@Ko@_@mB?AYeB"}, "start_location": {"lat": 54.0480988, "lng": -2.8067478}, "travel_mode": "DRIVING"}, {"distance": {"text": "55 m", "value": 55}, "duration": {"text": "1 min", "value": 24}, "end_location": {"lat": 54.0486838, "lng": -2.8032631}, "html_instructions": "Continue onto <b>Market St</b>", "polyline": {"points": "wj{hIntbPGYGiC"}, "start_location": {"lat": 54.0485994, "lng": -2.8040831}, "travel_mode": "DRIVING"}, {"distance": {"text": "0.4 km", "value": 387}, "duration": {"text": "1 min", "value": 75}, "end_location": {"lat": 54.0509128, "lng": -2.8003297}, "html_instructions": "Turn <b>left</b> onto <b>China St</b>/<wbr/><b>A6</b><div style=\"font-size:0.9em\">Continue to follow A6</div>", "maneuver": "turn-left", "polyline": {"points": "gk{hIjobPmCAmCO[KSIIECAGGGEEGGIGIGMEMEMAG?IAK?Q?C@}@Cw@AWCs@AQIy@IeACe@CW"}, "start_location": {"lat": 54.0486838, "lng": -2.8032631}, "travel_mode": "DRIVING"}, {"distance": {"text": "30 m", "value": 30}, "duration": {"text": "1 min", "value": 6}, "end_location": {"lat": 54.0510099, "lng": -2.7998948}, "html_instructions": "Keep <b>left</b> to continue on <b>Cable St</b>/<wbr/><b>A6</b>", "maneuver": "keep-left", "polyline": {"points": "ey{hI`}aPKo@CMAIAO"}, "start_location": {"lat": 54.0509128, "lng": -2.8003297}, "travel_mode": "DRIVING"}], "traffic_speed_entry": [], "via_waypoint": []}], "overview_polyline": {"points": "k_{hI`vcPYHiCtAm@VGoAKuBUqGMwFMkCYwB_@oBa@_CGiCmCAmCO[K]OKI]a@M[GUAk@AuBEkAYwDU_BAO"}, "summary": "A6", "warnings": [], "waypoint_order": []}]